{
    "django_secret":"",
    "bitcoin_api_getBlockByNumber_url" : "https://blockchain.info/rawblock/",
    "bitcoin_api_lastBlockNumber_url" : "https://blockchain.info/q/getblockcount",
    "tron_api_getBlockByNumber_url":"https://api.trongrid.io/walletsolidity/getblockbynum",
    "etherscan_apikey": "",
    "ethereum_api_getBlockByNumber_url" : "https://api.etherscan.io/api?module=proxy&action=eth_getBlockByNumber&tag=",
    "ethereum_api_lastBlockNumber_url" : "https://api-ropsten.etherscan.io/api?module=proxy&action=eth_blockNumber&apikey=",
    "tron_api_lastBlockNumber_url" : "https://api.trongrid.io/wallet/getnowblock",
    "usdt_eth_contract_address" : "0xdAC17F958D2ee523a2206206994597C13D831ec7",
    "usdt_eth_decimal" : 6,
    "eth_node":"https://mainnet.infura.io/v3/068e5cac7d6f43de9218dc3a84b7c71e",
    "dai_eth_contract_address" : "0x6B175474E89094C44Da98b954EedeAC495271d0F",
    "dai_eth_decimal" : 18,
    "usdt_trx_contract_address" : "TR7NHqjeKQxGTCi8q8ZY4pL8otSzgjLj6t",
    "usdt_trx_decimal" : 6,
    "general_backend_url_for_webhook_callback":"",
    "tron_get_event_api":"https://api.trongrid.io/event/transaction/"
}